<?xml version="1.0" ?><annotation>
	<folder>1</folder>
	<filename>000985.jpg</filename>
	<path>/home/aistudio/dataset/JPEGImages/000985.jpg</path>
	<source>
		<database>Unknown</database>
	</source>
	<size>
		<width>960</width>
		<height>540</height>
		<depth>3</depth>
	</size>
	<segmented>0</segmented>
	<object>
		<name>fire</name>
		<pose>Unspecified</pose>
		<truncated>0</truncated>
		<difficult>0</difficult>
		<bndbox>
			<xmin>387</xmin>
			<ymin>131</ymin>
			<xmax>535</xmax>
			<ymax>268</ymax>
		</bndbox>
	</object>
</annotation>